xoa_core/__init__.py
xoa_core/controller.py
xoa_core/exceptions.py
xoa_core/types.py
xoa_core/core/__init__.py
xoa_core/core/const.py
xoa_core/core/exceptions.py
xoa_core/core/generic_types.py
xoa_core/core/plugin_abstract.py
xoa_core/core/executors/__init__.py
xoa_core/core/executors/_events.py
xoa_core/core/executors/exceptions.py
xoa_core/core/executors/executor.py
xoa_core/core/executors/executor_info.py
xoa_core/core/executors/executor_state.py
xoa_core/core/executors/executor_state_conditions.py
xoa_core/core/executors/manager.py
xoa_core/core/messenger/__init__.py
xoa_core/core/messenger/handler.py
xoa_core/core/messenger/misc.py
xoa_core/core/messenger/pipe.py
xoa_core/core/resources/__init__.py
xoa_core/core/resources/controller.py
xoa_core/core/resources/pool.py
xoa_core/core/resources/storage.py
xoa_core/core/resources/types.py
xoa_core/core/resources/resource/__init__.py
xoa_core/core/resources/resource/const.py
xoa_core/core/resources/resource/exceptions.py
xoa_core/core/resources/resource/facade.py
xoa_core/core/resources/resource/misc.py
xoa_core/core/resources/resource/models/__decorator.py
xoa_core/core/resources/resource/models/__init__.py
xoa_core/core/resources/resource/models/module.py
xoa_core/core/resources/resource/models/port.py
xoa_core/core/resources/resource/models/tester.py
xoa_core/core/resources/resource/models/types.py
xoa_core/core/test_suites/__init__.py
xoa_core/core/test_suites/_loader.py
xoa_core/core/test_suites/controller.py
xoa_core/core/test_suites/datasets.py
xoa_core/core/utils/__init__.py
xoa_core/core/utils/observer.py
xoa_core/core/utils/validators.py
xoa_core-2.0.8.dist-info/LICENSE
xoa_core-2.0.8.dist-info/METADATA
xoa_core-2.0.8.dist-info/WHEEL
xoa_core-2.0.8.dist-info/top_level.txt
xoa_core-2.0.8.dist-info/RECORD
