Metadata-Version: 2.1
Name: xoa-core
Version: 2.0.8
Summary: Xena Open Automation framework for Xena test suite execution, integration, and development.
Home-page: https://github.com/xenanetworks/open-automation-core
Author: Artem Constantinov, Leonard Yu
Author-email: aco@xenanetworks.com, hyu@xenanewtorks.com
Maintainer: Xena Networks
Maintainer-email: support@xenanetworks.com
License: Apache 2.0
Classifier: Development Status :: 5 - Production/Stable
Classifier: Intended Audience :: Developers
Classifier: Topic :: Software Development :: Libraries :: Application Frameworks
Classifier: License :: OSI Approved :: Apache Software License
Classifier: Programming Language :: Python :: 3.8
Classifier: Programming Language :: Python :: 3.9
Classifier: Programming Language :: Python :: 3.10
Classifier: Programming Language :: Python :: 3.11
Requires-Python: >=3.8.9
License-File: LICENSE
Requires-Dist: xoa_driver>=2.0
Requires-Dist: pydantic==1.10.2
Requires-Dist: semver
Requires-Dist: oyaml
